jproperties.py
jproperties-2.1.1.dist-info/LICENSE
jproperties-2.1.1.dist-info/METADATA
jproperties-2.1.1.dist-info/WHEEL
jproperties-2.1.1.dist-info/entry_points.txt
jproperties-2.1.1.dist-info/top_level.txt
jproperties-2.1.1.dist-info/RECORD
