Metadata-Version: 1.1
Name: jproperties
Version: 2.1.1
Summary: Java Property file parser and writer for Python
Home-page: https://github.com/Tblue/python-jproperties
Author: Tilman Blumenbach
Author-email: tilman+pypi@ax86.net
License: BSD 3-Clause License; partially licensed under the Python Software Foundation License
Keywords: java property properties file parser reader writer
Platform: UNKNOWN
Classifier: Development Status :: 5 - Production/Stable
Classifier: Intended Audience :: Developers
Classifier: Intended Audience :: Information Technology
Classifier: License :: OSI Approved :: BSD License
Classifier: Operating System :: OS Independent
Classifier: Programming Language :: Python :: 2.7
Classifier: Programming Language :: Python :: 3.5
Classifier: Programming Language :: Python :: 3.6
Classifier: Programming Language :: Python :: 3.7
Classifier: Programming Language :: Python :: 3.8
Classifier: Programming Language :: Python :: 3.9
Classifier: Programming Language :: Python :: 3.10
Classifier: Topic :: Software Development
